matter_server/__init__.py
matter_server/py.typed
matter_server/client/__init__.py
matter_server/client/client.py
matter_server/client/connection.py
matter_server/client/exceptions.py
matter_server/client/models/__init__.py
matter_server/client/models/device_types.py
matter_server/client/models/node.py
matter_server/common/__init__.py
matter_server/common/const.py
matter_server/common/custom_clusters.py
matter_server/common/errors.py
matter_server/common/models.py
matter_server/common/helpers/api.py
matter_server/common/helpers/json.py
matter_server/common/helpers/logger.py
matter_server/common/helpers/util.py
matter_server/server/__init__.py
matter_server/server/__main__.py
matter_server/server/client_handler.py
matter_server/server/const.py
matter_server/server/device_controller.py
matter_server/server/sdk.py
matter_server/server/server.py
matter_server/server/stack.py
matter_server/server/storage.py
matter_server/server/vendor_info.py
matter_server/server/helpers/__init__.py
matter_server/server/helpers/attributes.py
matter_server/server/helpers/custom_web_runner.py
matter_server/server/helpers/paa_certificates.py
matter_server/server/helpers/utils.py
matter_server/server/ota/__init__.py
matter_server/server/ota/dcl.py
matter_server/server/ota/provider.py
ks_python_matter_server-6.3.0.dist-info/LICENSE
ks_python_matter_server-6.3.0.dist-info/METADATA
ks_python_matter_server-6.3.0.dist-info/WHEEL
ks_python_matter_server-6.3.0.dist-info/entry_points.txt
ks_python_matter_server-6.3.0.dist-info/top_level.txt
ks_python_matter_server-6.3.0.dist-info/RECORD
