Metadata-Version: 2.1
Name: ks-python-matter-server
Version: 6.3.0
Summary: Python Matter WebSocket Server
Author-email: The KS Assistant Authors <hello@home-assistant.io>
License: Apache-2.0
Platform: any
Classifier: Development Status :: 3 - Alpha
Classifier: Intended Audience :: Developers
Classifier: Environment :: Console
Classifier: Programming Language :: Python :: 3.11
Classifier: Programming Language :: Python :: 3.12
Classifier: Topic :: Home Automation
Requires-Python: >=3.11
License-File: LICENSE
Requires-Dist: aiohttp
Requires-Dist: aiorun
Requires-Dist: async-timeout
Requires-Dist: coloredlogs
Requires-Dist: orjson
Requires-Dist: home-assistant-chip-clusters==2024.7.0
Provides-Extra: server
Requires-Dist: aiohttp==3.9.5; extra == "server"
Requires-Dist: aiorun==2024.5.1; extra == "server"
Requires-Dist: async-timeout==4.0.3; extra == "server"
Requires-Dist: coloredlogs==15.0.1; extra == "server"
Requires-Dist: cryptography==42.0.8; extra == "server"
Requires-Dist: orjson==3.10.6; extra == "server"
Requires-Dist: zeroconf==0.132.2; extra == "server"
Requires-Dist: home-assistant-chip-core==2024.7.0; extra == "server"
Provides-Extra: test
Requires-Dist: codespell==2.3.0; extra == "test"
Requires-Dist: isort==5.13.2; extra == "test"
Requires-Dist: mypy==1.10.1; extra == "test"
Requires-Dist: pre-commit==3.7.1; extra == "test"
Requires-Dist: pre-commit-hooks==4.6.0; extra == "test"
Requires-Dist: pylint==3.2.5; extra == "test"
Requires-Dist: pytest==8.2.2; extra == "test"
Requires-Dist: pytest-asyncio==0.23.7; extra == "test"
Requires-Dist: pytest-aiohttp==1.0.5; extra == "test"
Requires-Dist: pytest-cov==5.0.0; extra == "test"
Requires-Dist: ruff==0.5.2; extra == "test"
Requires-Dist: tomli==2.0.1; extra == "test"
